py_dbar/__init__.py
py_dbar/dBar.py
py_dbar/info.py
py_dbar/k_grid.py
py_dbar/read_data.py
py_dbar/scattering.py
py_dbar/sim.py
py_dbar/sim_data.py
py_dbar-1.0.0.dist-info/LICENSE.txt
py_dbar-1.0.0.dist-info/METADATA
py_dbar-1.0.0.dist-info/WHEEL
py_dbar-1.0.0.dist-info/top_level.txt
py_dbar-1.0.0.dist-info/RECORD
