Metadata-Version: 2.1
Name: py-dbar
Version: 1.0.0
Summary: Dbar Algorithm for EIT
Home-page: UNKNOWN
Author: NablaIp
Author-email: <ivanpombo.eigen@gmail.com>
License: UNKNOWN
Keywords: python,EIT,DBar Algorithm
Platform: UNKNOWN
Classifier: Development Status :: 4 - Beta
Classifier: Intended Audience :: Science/Research
License-File: LICENSE.txt
Requires-Dist: numpy
Requires-Dist: scipy
Requires-Dist: pyamg
Requires-Dist: pyeit
Requires-Dist: matplotlib
